latviastreetify/__init__.py
latviastreetify/cli.py
latviastreetify/resolvers.py
latviastreetify/data/Apkaimes.cpg
latviastreetify/data/Apkaimes.dbf
latviastreetify/data/Apkaimes.prj
latviastreetify/data/Apkaimes.shp
latviastreetify/data/Apkaimes.shx
latviastreetify/data/adreses.cpg
latviastreetify/data/adreses.dbf
latviastreetify/data/adreses.prj
latviastreetify/data/adreses.qpj
latviastreetify/data/adreses.shp
latviastreetify/data/adreses.shx
latviastreetify/tests/test_resolver.py
latviastreetify-0.2.0.dist-info/LICENSE
latviastreetify-0.2.0.dist-info/WHEEL
latviastreetify-0.2.0.dist-info/METADATA
latviastreetify-0.2.0.dist-info/RECORD
