Metadata-Version: 2.1
Name: latviastreetify
Version: 0.2.0
Summary: module that help get streets and neiborhoods from latitude longitude
Author-email: William Droz <william.droz@idiap.ch>
Classifier: License :: OSI Approved :: MIT License
Requires-Dist: geopandas >= 0.13.2,<1.0.0
Requires-Dist: pyproj >=3.6.0,<4
Requires-Dist: typer[all] >= 0.9.0,<1.0.0 ; extra == "cli"
Requires-Dist: black == 22.3.0 ; extra == "dev"
Requires-Dist: coverage >= 6.4.2,<7.0.0 ; extra == "dev"
Requires-Dist: flake8 >=3.8.3,<4.0.0 ; extra == "dev"
Requires-Dist: mypy >=0.971,<1.0 ; extra == "dev"
Requires-Dist: pre-commit >=3.3.3,<4.0.0 ; extra == "dev"
Requires-Dist: pytest >=7.1.2,<8.0.0 ; extra == "dev"
Project-URL: Home, https://gitlab.idiap.ch/socialcomputing/Icarus/latvian_streets_neighborhoods
Provides-Extra: cli
Provides-Extra: dev
